{
  "name": "${project.name}",
  "version": "${project.version}",
  "description": "${project.description}",
  "platform": "complete",
  "dependencies": [
    {
      "name": "app-platform-complete",
      "version": "^VERSION",
      "preRelease": "false"
    },
    {
      "name": "app-marc-storage",
      "version": "^VERSION",
      "preRelease": "false"
    }
  ],
  "modules": [
    {
      "name": "mod-oai-pmh",
      "version": "^VERSION",
      "preRelease": "false"
    },
    {
      "name": "edge-oai-pmh",
      "version": "^VERSION",
      "preRelease": "false"
    }
  ],
  "uiModules": [
    {
      "name": "folio_oai-pmh",
      "version": "^VERSION",
      "preRelease": "false"
    }
  ]
}
